ace/__init__.py
ace/adaptation.py
ace/async_learning.py
ace/features.py
ace/llm.py
ace/prompts.py
ace/prompts_v2.py
ace/prompts_v2_1.py
ace/py.typed
ace/roles.py
ace/skillbook.py
ace/updates.py
ace/llm_providers/__init__.py
ace/llm_providers/instructor_client.py
ace/llm_providers/langchain_client.py
ace/llm_providers/litellm_client.py
ace/observability/__init__.py
ace/observability/opik_integration.py
ace/observability/tracers.py
ace_framework-0.7.2.dist-info/licenses/LICENSE
ace_framework-0.7.2.dist-info/METADATA
ace_framework-0.7.2.dist-info/WHEEL
ace_framework-0.7.2.dist-info/top_level.txt
ace_framework-0.7.2.dist-info/RECORD
