Metadata-Version: 2.4
Name: ace-framework
Version: 0.7.2
Summary: Build self-improving AI agents that learn from experience
Author-email: "Kayba.ai" <hello@kayba.ai>
Maintainer-email: "Kayba.ai" <hello@kayba.ai>
License: MIT
Project-URL: Homepage, https://kayba.ai
Project-URL: Documentation, https://github.com/Kayba-ai/agentic-context-engine#readme
Project-URL: Repository, https://github.com/Kayba-ai/agentic-context-engine
Project-URL: Issues, https://github.com/Kayba-ai/agentic-context-engine/issues
Keywords: ai,llm,agents,machine-learning,self-improvement,context-engineering,ace,openai,anthropic,claude,gpt
Classifier: Development Status :: 4 - Beta
Classifier: Intended Audience :: Developers
Classifier: License :: OSI Approved :: MIT License
Classifier: Programming Language :: Python :: 3
Classifier: Programming Language :: Python :: 3.12
Classifier: Topic :: Scientific/Engineering :: Artificial Intelligence
Classifier: Topic :: Software Development :: Libraries :: Python Modules
Requires-Python: ==3.12.*
License-File: LICENSE
Requires-Dist: litellm>=1.78.0
Requires-Dist: pydantic>=2.0.0
Requires-Dist: python-dotenv>=1.0.0
Requires-Dist: python-toon>=0.1.0
Requires-Dist: tenacity>=8.0.0
Requires-Dist: instructor>=1.0.0
Requires-Dist: browser-use>=0.9.1
Provides-Extra: browser-use
Requires-Dist: browser-use>=0.9.0; extra == "browser-use"
Provides-Extra: observability
Requires-Dist: opik>=1.8.0; extra == "observability"
Provides-Extra: langchain
Requires-Dist: langchain-openai>=0.3.35; extra == "langchain"
Requires-Dist: langchain-anthropic>=0.3.0; extra == "langchain"
Requires-Dist: langchain-litellm>=0.2.0; extra == "langchain"
Requires-Dist: langgraph>=0.2.0; extra == "langchain"
Provides-Extra: transformers
Requires-Dist: transformers>=4.30.0; extra == "transformers"
Requires-Dist: torch>=2.0.0; extra == "transformers"
Requires-Dist: accelerate>=0.20.0; extra == "transformers"
Provides-Extra: all
Requires-Dist: browser-use>=0.9.0; extra == "all"
Requires-Dist: opik>=1.8.0; extra == "all"
Requires-Dist: langchain-openai>=0.3.35; extra == "all"
Requires-Dist: langchain-anthropic>=0.3.0; extra == "all"
Requires-Dist: langchain-litellm>=0.2.0; extra == "all"
Requires-Dist: langgraph>=0.2.0; extra == "all"
Requires-Dist: transformers>=4.30.0; extra == "all"
Requires-Dist: torch>=2.0.0; extra == "all"
Requires-Dist: accelerate>=0.20.0; extra == "all"
Dynamic: license-file
